obfusk/__init__.py
obfusk/__main__.py
obfusk/immutable.py
obfusk/lazy.py
obfusk-0.0.1.dist-info/DESCRIPTION.rst
obfusk-0.0.1.dist-info/METADATA
obfusk-0.0.1.dist-info/RECORD
obfusk-0.0.1.dist-info/WHEEL
obfusk-0.0.1.dist-info/metadata.json
obfusk-0.0.1.dist-info/top_level.txt
